<?xml version='1.0' encoding='utf-8'?>
<root><id>15638</id><name>Convoy no Nazo</name><description>OverviewToransufoumaou: Konboi no Nazo (translated to Transformers: Mystery of Convoy) is a 2D sidescrolling action platformer developed by ISCO and published by TAKARA for the Nintendo Entertainment System (in Japan only) on Decmber 5, 1986. Set in the first-generation Transformers universe, players control Autobot Ultra Magnus as he storms through various Decepticon strongholds to find the whereabouts of Autobot leader Convoy (known worldwide as Optimus Prime).GameplayConvoy no Nazo consists of 9 stages, each ending in a boss battle. Players can move and shoot as well as transform into a more maneuverable vehicle mode. The game is so difficult, most players do not usually pass the first stage. The 9th stage is a maze which, if not completed in precisely the right way, will infinitely loop. Warp Zones can be found by locating Bumblebee in some levels.UnlockablesPlayers can unlock a Rodimus Prime skin by collecting the letters that spell RODIMUS in stages 1,2,4,5,7,8,9. His robot sprite is a recolored Ultra Magnus sprite, but he has a completely different vehicle sprite.</description><genres><genre id="1">Action</genre></genres><similar_games><game id="15544">Super Mario Bros.</game><game id="5251">Mega Man</game><game id="41288">Choujikuu Yousai Macross</game><game id="36484">Daiva 6: Imperial of Nirsartia</game></similar_games><image>http://static.giantbomb.com/uploads/scale_avatar/0/5765/228441-convoy_box.png</image></root>