<?xml version='1.0' encoding='utf-8'?>
<root><id>21969</id><name>Starship Catan</name><description>OverviewStarship Catan is a PC version of the eponymous two-player Card/Board game designed by Klaus Teuber. Release NotesStarship Catan was released in Germany as Sternenschiff Catan in Fall 2003. An English translation was rumored as of early 2004 on BoardGameGeek, but there is no evidence that this occured.</description><genres><genre id="4">Adventure</genre><genre id="13">Card Game</genre><genre id="14">Trivia/Board Game</genre></genres><similar_games><game id="21010">Catan</game><game id="10233">Catan: Die Erste Insel</game><game id="5913">Catan: Das Kartenspiel</game><game id="27816">Greed Corp</game></similar_games><image>http://static.giantbomb.com/uploads/scale_avatar/0/913/268695-sternenschiff_catan_pc_spiel2.jpg</image></root>