<?xml version='1.0' encoding='utf-8'?>
<root><id>35474</id><name>Naval Warfare</name><description>OverviewIn an alternate world of Victorian architecture and industrial contraptions, war is lead mainly by means of aquatic machinery. The player takes the role of a ship commander and must eradicate his nation from invading enemy forces, as well as a mysterious new warmonger.PC System RequirementsOperating System: Windows XP SP3, Windows Vista, Windows 7Processor: Intel or AMD Dual-Core Prozessor (1.9 GHz) or betterRAM Memory: 2GBHard Disk Space: 1.5 GB hard drive spaceVideo Card: NVIDIA Geforce GTS250 / ATI Radeon HD4800 or betterDirectX®: DirectX 9.0cSound Card: DirectX 9c compatible</description><genres><genre id="31">Dual-Joystick Shooter</genre></genres><similar_games><game id="13924">Cobra Triangle</game></similar_games><image>http://static.giantbomb.com/uploads/scale_avatar/1/13692/1796904-header_292x136.jpg</image></root>