<?xml version='1.0' encoding='utf-8'?>
<root><id>3553</id><name>Asterix at the Olympic Games</name><description>PC System RequirementsCPU: 1 GHzRAM: 256 MB RAM / 1 GB for VistaVGA: 64MBDX: DirectX 9.0cOS: Windows XP/VistaHDD: 3.5 GBXbox 360 Game InstallationAsterix at the Olympic Games requires 6.0GB of space to install on an Xbox 360 HDD.</description><genres><genre id="1">Action</genre><genre id="3">Sports</genre><genre id="42">Track &amp; Field</genre></genres><similar_games><game id="15205">Mario &amp; Sonic at the Olympic Games</game></similar_games><image>http://static.giantbomb.com/uploads/scale_avatar/20/207993/2543106-1909749-942189_97646_front.jpg</image></root>