<?xml version='1.0' encoding='utf-8'?>
<root><id>10560</id><name>Money Mad</name><description>OverviewMoney Mad is a strategy/board game developed by Ravensburger Interactive Media and published by 1C Company for the PC platform. Money Mad was never released outside of European countries.</description><genres><genre id="2">Strategy</genre><genre id="14">Trivia/Board Game</genre></genres><similar_games /><image>http://static.giantbomb.com/uploads/scale_avatar/10/103881/2148110-cover.jpg</image></root>