<?xml version='1.0' encoding='utf-8'?>
<root><id>13497</id><name>Trash It</name><description>Trash It was a pretty obscure side-scrolling Playstation and PC title. Released in the US July 1997.  You are Jack Hammer, your goal is to find a better hammer.  The game consists of you running around, smashing structures and objects with your massive hammer, then either Smashing the rats who come out of the debris.. or Vacuum it all up in one go.</description><genres><genre id="41">Platformer</genre></genres><similar_games /><image>http://static.giantbomb.com/uploads/scale_avatar/1/12741/1391590-cover.jpg</image></root>