<?xml version='1.0' encoding='utf-8'?>
<root><id>16390</id><name>SpellForce: Universe</name><description>This package contains the following games:Spellforce 1SpellForce: The Order of DawnSpellForce: The Breath of WinterSpellForce: Shadow of the PhoenixSpellforce 2SpellForce 2: Shadow WarsSpellForce 2: Dragon StormSystem RequirementsOS: Windows速 2000, XP, Vista 32BitCPU: Intel Pentium速 4 1.5GHzRAM: 512 MB RAMVIDEO: 3D Graphics Card with 128 MB RAM (compatible with GeForce 4 Ti or higher)SOUND: DirectX速 compatibleDirectX速 9.0c</description><genres><genre id="2">Strategy</genre><genre id="5">Role-Playing</genre></genres><similar_games /><image>http://static.giantbomb.com/uploads/scale_avatar/11/117587/2285047-spellforcebox_front.jpg</image></root>