<?xml version='1.0' encoding='utf-8'?>
<root><id>24778</id><name>Letter Zap!</name><description>OverviewLetter Zap! is a puzzle game developed and published by ZAPiT Games for the Game Wave platform.GameplayIn Letter Zap! four players simultaneously have a grid of letters in which the goal is to find as many words as possible. In order to make a word the letters must the touching, and any letter can only be used once in a single word. The game plays almost identically to Boggle.</description><genres><genre id="18">Puzzle</genre></genres><similar_games><game id="38075">Wordament</game><game id="1071">Boggle</game></similar_games><image>http://static.giantbomb.com/uploads/scale_avatar/0/4647/832844-letterf.jpg</image></root>