<?xml version='1.0' encoding='utf-8'?>
<root><id>25658</id><name>Math Blazer</name><description>Math Blazer is a board game based on the popular game where you have to build words linking letters. The difference comes when you have to build math functions instead of words.    </description><genres><genre id="8">Educational</genre></genres><similar_games><game id="24922">Brain Age Express: Math</game><game id="19476">Basic Math</game><game id="26020">Math Blaster in the Prime Adventure</game><game id="72">Math Blaster: Episode 1 - In Search of Spot</game><game id="15303">Disney's Math Quest with Aladdin</game><game id="6847">Math Workshop</game><game id="17981">Math Blaster!</game><game id="18503">Donkey Kong Jr. Math</game><game id="4279">Math-A-Magic! / Echo!</game><game id="798">Math Rescue</game><game id="14275">Yogi Bear's Math Adventures</game></similar_games><image>http://static.giantbomb.com/uploads/scale_avatar/8/82482/1368767-cabecera3.jpg</image></root>