<?xml version='1.0' encoding='utf-8'?>
<root><id>30095</id><name>Mario Lemieux Hockey</name><description>Overview Mario Lemieux Hockey is a hockey video game for the Sega Genesis.  It does not feature an NHL or NHLPA (the NHL hockey players' union) license, meaning there are no official teams in the game and Mario Lemieux is the only player in the game with the same name of a real-life player.</description><genres><genre id="39">Hockey</genre></genres><similar_games><game id="22497">Brett Hull Hockey</game><game id="15229">Wayne Gretzky Hockey</game><game id="26553">TV Sports Hockey</game><game id="11129">NHL Hockey</game><game id="5450">NHLPA Hockey '93</game></similar_games><image>http://static.giantbomb.com/uploads/scale_avatar/3/38151/1284572-mario_lemieux_hockey.jpg</image></root>